[
  { "charactor_id": 112, "name": "Kingdom Hearts III" },
  { "charactor_id": 450, "name": "TaleSpin (NES video game)" },
  { "charactor_id": 450, "name": "TaleSpin (Sega Genesis Video Game)" },
  { "charactor_id": 450, "name": "The Jungle Book (video game)" },
  { "charactor_id": 450, "name": "The Jungle Book Groove Party" },
  { "charactor_id": 450, "name": "Disney Universe" },
  { "charactor_id": 450, "name": "Kinect Disneyland Adventures" },
  { "charactor_id": 450, "name": "Disney Infinity (series)" },
  { "charactor_id": 450, "name": "Disney Crossy Road" },
  { "charactor_id": 450, "name": "Disney Emoji Blitz" },
  { "charactor_id": 450, "name": "Disney Magic Kingdoms" },
  { "charactor_id": 450, "name": "Kingdom Hearts Union χ" },
  { "charactor_id": 450, "name": "Disney Heroes: Battle Mode" },
  { "charactor_id": 450, "name": "Disney Sorcerer's Arena" },
  { "charactor_id": 450, "name": "Just Dance: Disney Party" },
  { "charactor_id": 566, "name": "The Haunted Mansion (video game)" },
  { "charactor_id": 566, "name": "Kinect Disneyland Adventures" },
  { "charactor_id": 566, "name": "Disney Crossy Road" },
  { "charactor_id": 206, "name": "Treasure Planet: Battle at Procyon" },
  { "charactor_id": 206, "name": "Disney Sorcerer's Arena" },
  { "charactor_id": 206, "name": "Disney Heroes: Battle Mode" },
  { "charactor_id": 291, "name": "Kingdom Hearts: Birth by Sleep" },
  { "charactor_id": 291, "name": "Kingdom Hearts coded" },
  { "charactor_id": 291, "name": "Kingdom Hearts 3D: Dream Drop Distance" },
  {
    "charactor_id": 291,
    "name": "Kingdom Hearts HD II.8 Final Chapter Prologue"
  },
  { "charactor_id": 291, "name": "Kingdom Hearts III" },
  { "charactor_id": 291, "name": "Disney Emoji Blitz" },
  { "charactor_id": 291, "name": "Disney Tsum Tsum" }
]
